ptag/__init__.py
ptag/elements.py
ptag/gen_elements.py
ptag/tag.py
ptag-0.2.3.dist-info/LICENSE
ptag-0.2.3.dist-info/METADATA
ptag-0.2.3.dist-info/WHEEL
ptag-0.2.3.dist-info/RECORD
