Metadata-Version: 2.1
Name: ptag
Version: 0.2.3
Summary: generate html/svg tags hierarchy with context manager
Home-page: https://github.com/hoishing/ptag
License: MIT
Keywords: template,html,xml,svg,tag
Author: Kelvin Ng
Author-email: hoishing@gmail.com
Requires-Python: >=3.12,<4.0
Classifier: Development Status :: 4 - Beta
Classifier: Intended Audience :: Developers
Classifier: License :: OSI Approved :: MIT License
Classifier: Programming Language :: Python :: 3
Classifier: Programming Language :: Python :: 3.12
Classifier: Topic :: Internet :: WWW/HTTP :: Dynamic Content
Project-URL: Repository, https://github.com/hoishing/ptag
